deltachat_rpc_server/LICENSE
deltachat_rpc_server/README.md
deltachat_rpc_server/__init__.py
deltachat_rpc_server/deltachat-rpc-server
deltachat_rpc_server-2.39.0.dist-info/METADATA
deltachat_rpc_server-2.39.0.dist-info/WHEEL
deltachat_rpc_server-2.39.0.dist-info/entry_points.txt
deltachat_rpc_server-2.39.0.dist-info/RECORD
