Metadata-Version: 2.1
Name: deltachat-rpc-server
Version: 2.39.0
Summary: Delta Chat JSON-RPC server
